README.md
setup.py
pyfbi/__init__.py
pyfbi/fbi_stat.py
pyfbi/pyfbi_viz.py
pyfbi/scheduler.py
pyfbi/watcher.py
pyfbi.egg-info/PKG-INFO
pyfbi.egg-info/SOURCES.txt
pyfbi.egg-info/dependency_links.txt
pyfbi.egg-info/entry_points.txt
pyfbi.egg-info/requires.txt
pyfbi.egg-info/top_level.txt
pyfbi/visualize/__init__.py
pyfbi/visualize/server.py
pyfbi/visualize/static/css/datatables.min.css
pyfbi/visualize/static/css/index.css
pyfbi/visualize/static/css/DataTables-1.10.16/images/sort_asc.png
pyfbi/visualize/static/css/DataTables-1.10.16/images/sort_asc_disabled.png
pyfbi/visualize/static/css/DataTables-1.10.16/images/sort_both.png
pyfbi/visualize/static/css/DataTables-1.10.16/images/sort_desc.png
pyfbi/visualize/static/css/DataTables-1.10.16/images/sort_desc_disabled.png
pyfbi/visualize/static/img/favicon.ico
pyfbi/visualize/static/img/pyfbi.png
pyfbi/visualize/static/js/Chart.min.js
pyfbi/visualize/static/js/datatables.min.js
pyfbi/visualize/static/js/index.js
pyfbi/visualize/static/js/palette.js
pyfbi/visualize/static/js/reconnecting-websocket.min.js
pyfbi/visualize/templates/base.html
pyfbi/visualize/templates/index.html