Metadata-Version: 1.1
Name: pyfbi
Version: 0.2.0
Summary: pyFBI enables 'as much as needed' profiling by decorator
Home-page: https://github.com/icoxfog417/pyfbi
Author: icoxfog417
Author-email: icoxfog417@yahoo.co.jp
License: MIT
Keywords: performance-analysis pstat profile
Platform: UNKNOWN
Classifier: Programming Language :: Python :: 3.6
